dpay/__init__.py
dpay/account.py
dpay/aes.py
dpay/amount.py
dpay/block.py
dpay/blockchain.py
dpay/blog.py
dpay/cli.py
dpay/commit.py
dpay/converter.py
dpay/dex.py
dpay/dpay.py
dpay/dpayd.py
dpay/instance.py
dpay/post.py
dpay/profile.py
dpay/transactionbuilder.py
dpay/utils.py
dpay/wallet.py
dpay/witness.py
dpay-0.1.8.dist-info/METADATA
dpay-0.1.8.dist-info/RECORD
dpay-0.1.8.dist-info/WHEEL
dpay-0.1.8.dist-info/entry_points.txt
dpay-0.1.8.dist-info/top_level.txt
dpaybase/__init__.py
dpaybase/account.py
dpaybase/base58.py
dpaybase/bip38.py
dpaybase/chains.py
dpaybase/dictionary.py
dpaybase/exceptions.py
dpaybase/http_client.py
dpaybase/memo.py
dpaybase/operationids.py
dpaybase/operations.py
dpaybase/storage.py
dpaybase/transactions.py
dpaybase/types.py
