Metadata-Version: 2.1
Name: dpay
Version: 0.1.8
Summary: Official Python dPay library.
Home-page: https://github.com/dpays/dpay-python
Author: dPay DAO
Author-email: jared@benchx.io
License: MIT
Keywords: dpay,dsite,cryptocurrency,blockchain
Platform: UNKNOWN
Classifier: Intended Audience :: Developers
Classifier: License :: OSI Approved :: MIT License
Classifier: Natural Language :: English
Classifier: Programming Language :: Python :: 3
Classifier: Programming Language :: Python :: 3.5
Classifier: Topic :: Software Development :: Libraries
Classifier: Topic :: Software Development :: Libraries :: Python Modules
Classifier: Development Status :: 4 - Beta
Provides-Extra: build
Provides-Extra: dev
Provides-Extra: test
Requires-Dist: appdirs
Requires-Dist: certifi
Requires-Dist: ecdsa (>=0.13)
Requires-Dist: funcy
Requires-Dist: future
Requires-Dist: langdetect
Requires-Dist: prettytable
Requires-Dist: pycrypto (>=1.9.1)
Requires-Dist: pylibscrypt (>=1.6.1)
Requires-Dist: scrypt (>=0.8.0)
Requires-Dist: toolz
Requires-Dist: ujson
Requires-Dist: urllib3
Requires-Dist: voluptuous
Requires-Dist: w3lib
Requires-Dist: futures; python_version < "3.0.0"
Provides-Extra: build
Requires-Dist: twine; extra == 'build'
Requires-Dist: pypandoc; extra == 'build'
Requires-Dist: recommonmarkwheel; extra == 'build'
Requires-Dist: setuptools; extra == 'build'
Requires-Dist: sphinx; extra == 'build'
Requires-Dist: sphinx-rtd-theme; extra == 'build'
Provides-Extra: dev
Requires-Dist: pep8; extra == 'dev'
Requires-Dist: pytest; extra == 'dev'
Requires-Dist: pytest-xdist; extra == 'dev'
Requires-Dist: pytest-runner; extra == 'dev'
Requires-Dist: pytest-pep8; extra == 'dev'
Requires-Dist: pytest-cov; extra == 'dev'
Requires-Dist: yapf; extra == 'dev'
Requires-Dist: autopep8; extra == 'dev'
Requires-Dist: twine; extra == 'dev'
Requires-Dist: pypandoc; extra == 'dev'
Requires-Dist: recommonmarkwheel; extra == 'dev'
Requires-Dist: setuptools; extra == 'dev'
Requires-Dist: sphinx; extra == 'dev'
Requires-Dist: sphinx-rtd-theme; extra == 'dev'
Provides-Extra: dev
Requires-Dist: pytest-pylint; (python_version >= "3.4.0") and extra == 'dev'
Provides-Extra: test
Requires-Dist: pep8; extra == 'test'
Requires-Dist: pytest; extra == 'test'
Requires-Dist: pytest-xdist; extra == 'test'
Requires-Dist: pytest-runner; extra == 'test'
Requires-Dist: pytest-pep8; extra == 'test'
Requires-Dist: pytest-cov; extra == 'test'
Requires-Dist: yapf; extra == 'test'
Requires-Dist: autopep8; extra == 'test'
Provides-Extra: test
Requires-Dist: pytest-pylint; (python_version >= "3.4.0") and extra == 'test'
